signnow_client/__init__.py
signnow_client/client.py
signnow_client/client_base.py
signnow_client/client_document_groups.py
signnow_client/client_documents.py
signnow_client/client_other.py
signnow_client/config.py
signnow_client/exceptions.py
signnow_client/models.py
signnow_client/utils.py
signnow_client/models/__init__.py
signnow_client/models/document_groups.py
signnow_client/models/folders_lite.py
signnow_client/models/other_models.py
signnow_client/models/templates_and_documents.py
sn_mcp_server/__init__.py
sn_mcp_server/_version.py
sn_mcp_server/app.py
sn_mcp_server/auth.py
sn_mcp_server/cli.py
sn_mcp_server/config.py
sn_mcp_server/server.py
sn_mcp_server/token_provider.py
sn_mcp_server/tools/__init__.py
sn_mcp_server/tools/create_from_template.py
sn_mcp_server/tools/document.py
sn_mcp_server/tools/document_download_link.py
sn_mcp_server/tools/embedded_editor.py
sn_mcp_server/tools/embedded_invite.py
sn_mcp_server/tools/embedded_sending.py
sn_mcp_server/tools/invite_status.py
sn_mcp_server/tools/list_documents.py
sn_mcp_server/tools/list_templates.py
sn_mcp_server/tools/models.py
sn_mcp_server/tools/send_invite.py
sn_mcp_server/tools/signing_link.py
sn_mcp_server/tools/signnow.py
sn_mcp_server/tools/utils.py
signnow_mcp_server-0.5.2.dist-info/METADATA
signnow_mcp_server-0.5.2.dist-info/WHEEL
signnow_mcp_server-0.5.2.dist-info/entry_points.txt
signnow_mcp_server-0.5.2.dist-info/licenses/LICENSE.md
signnow_mcp_server-0.5.2.dist-info/RECORD
