Metadata-Version: 2.4
Name: signnow-mcp-server
Version: 0.5.2
Summary: A Model Context Protocol (MCP) server that provides SignNow API integration capabilities.
License-File: LICENSE.md
Requires-Python: >=3.10
Requires-Dist: cryptography>=42
Requires-Dist: fastmcp<3,>=2.13.0
Requires-Dist: httpx[http2]>=0.25
Requires-Dist: mcp[cli]<2,>=1.10
Requires-Dist: pydantic-settings>=2.0
Requires-Dist: pydantic>=2.0
Requires-Dist: pyjwt[crypto]>=2.8
Requires-Dist: starlette>=0.27
Requires-Dist: typer>=0.9
Requires-Dist: uvicorn[standard]>=0.24
Provides-Extra: langchain
Requires-Dist: langchain-core>=0.1.0; extra == 'langchain'
Requires-Dist: langchain-mcp-adapters>=0.1.0; extra == 'langchain'
Requires-Dist: langchain-openai>=0.1.0; extra == 'langchain'
Requires-Dist: langchain>=0.1.0; extra == 'langchain'
Provides-Extra: llamaindex
Requires-Dist: llama-index-core>=0.10.0; extra == 'llamaindex'
Requires-Dist: llama-index-llms-openai>=0.1.0; extra == 'llamaindex'
Requires-Dist: llama-index-tools-mcp>=0.1.0; extra == 'llamaindex'
Requires-Dist: python-dotenv>=1.0.0; extra == 'llamaindex'
Provides-Extra: smolagents
Requires-Dist: mcpadapt>=0.1.11; extra == 'smolagents'
Requires-Dist: smolagents>=1.20; extra == 'smolagents'
Provides-Extra: test
Requires-Dist: httpx>=0.25; extra == 'test'
Requires-Dist: pytest-asyncio>=0.21; extra == 'test'
Requires-Dist: pytest-mock>=3.10; extra == 'test'
Requires-Dist: pytest>=7.0; extra == 'test'
